imagedataset/__init__.py
imagedataset/dataloaders.py
imagedataset/datasets.py
imagedataset/enums.py
imagedataset/imagedecoders.py
imagedataset/imageloaders.py
imagedataset/imageresizers.py
imagedataset/multidataset.py
imagedataset/operations.py
imagedataset/samplers.py
imagedataset/utils.py
torch_image_dataset-0.0.4.dist-info/LICENSE
torch_image_dataset-0.0.4.dist-info/METADATA
torch_image_dataset-0.0.4.dist-info/WHEEL
torch_image_dataset-0.0.4.dist-info/top_level.txt
torch_image_dataset-0.0.4.dist-info/RECORD
